{
  "$schema": "https://ui.shadcn.com/schema/registry-item.json",
  "name": "select",
  "title": "Select",
  "description": "Dropdown select using `ds-menu` internally. Supports placeholder, isInactive state, and custom chevron icon.",
  "type": "registry:ui",
  "meta": {
    "library": "@ds-mo/ui",
    "distribution": "npm",
    "storybook": "https://zainadeel.github.io/compomo/?path=/story/select",
    "consumption": {
      "install": "npm install @ds-mo/ui @ds-mo/tokens @ds-mo/icons",
      "cssSetup": "Import at your app entry point:\n  import '@ds-mo/tokens';        // or @ds-mo/tokens/css\n  import '@ds-mo/tokens/reset';\n  import '@ds-mo/tokens/globals';\nFor dark mode: set data-theme=\"dark\" on <html>.\nComponent CSS ships scoped inside each @ds-mo/ui custom-element import — no global @ds-mo/ui/css.",
      "register": "// Import only the <ds-*> tags your app uses:\nimport '@ds-mo/ui/dist/components/ds-select.js';\n\n// Angular: import proxies from '@ds-mo/ui/angular'\n// React: import { DsButton, … } from '@ds-mo/ui/react'",
      "usage": {
        "html": "<ds-select></ds-select>",
        "react": "<ds-select></ds-select>",
        "angular": "<ds-select></ds-select>"
      },
      "internalDependencies": [
        {
          "component": "Menu",
          "note": "Used internally by Select. Bundled in @ds-mo/ui."
        },
        {
          "component": "Text",
          "note": "Used internally by Select. Bundled in @ds-mo/ui."
        }
      ],
      "peerDependencies": {
        "required": [
          "@ds-mo/tokens >=2.9.0",
          "@ds-mo/icons ^5.0.1"
        ],
        "optional": [],
        "frameworks": "None — works with React 17+, Angular 12+, plain HTML, and any framework with Custom Element support."
      }
    },
    "props": {
      "value": {
        "type": "string | number",
        "required": true
      },
      "onChange": {
        "type": "(value: string | number) => void",
        "required": true
      },
      "options": {
        "type": "SelectOption[]",
        "required": true
      },
      "placeholder": {
        "type": "string",
        "default": "'Select option'"
      },
      "isInactive": {
        "type": "boolean",
        "default": "false",
        "description": "Disables interaction (25% opacity via ds-control-inactive)."
      },
      "chevronIcon": {
        "type": "IconComponent"
      }
    },
    "exports": [
      "Select"
    ],
    "types": [
      "SelectProps",
      "SelectOption"
    ]
  },
  "dependencies": [
    "@ds-mo/ui",
    "@ds-mo/tokens"
  ],
  "registryDependencies": [
    "menu",
    "text"
  ],
  "files": [
    {
      "path": "src/wc/components/Select/Select.css",
      "content": "/* ==========================================================================\n   Select — combobox-pattern select using ds-menu for the dropdown.\n   ========================================================================== */\n\n@import '../../utils/control-inactive.css';\n\n:host(.select-host) {\n  display: inline-block;\n  width: 100%;\n  position: relative;\n}\n\n/* Inactive: `.ds-control-inactive` (25% opacity). */\n\n/* ── Trigger button ──────────────────────────────────────────────────────── */\n\n.trigger {\n  display: inline-flex;\n  align-items: center;\n  justify-content: space-between;\n  width: 100%;\n  height: var(--dimension-size-400);\n  padding: 0 var(--dimension-space-075) 0 var(--dimension-space-100);\n  border: none;\n  border-radius: var(--dimension-radius-050);\n  background-color: var(--color-background-primary);\n  box-shadow: var(--effect-elevation-elevated-sm);\n  cursor: pointer;\n  box-sizing: border-box;\n  gap: var(--dimension-space-050);\n  font-family: inherit;\n  outline: none;\n\n  --_hover-bg: color-mix(in oklch, var(--color-background-primary) 90%, var(--color-foreground-primary));\n  --_pressed-bg: color-mix(in oklch, var(--color-background-primary) 85%, var(--color-foreground-primary));\n}\n\n.trigger:focus-visible {\n  outline: var(--dimension-stroke-width-025) solid var(--color-interaction-focus);\n  outline-offset: var(--dimension-space-025);\n}\n\n.trigger:hover:not(:disabled) {\n  background-color: var(--_hover-bg);\n}\n\n.trigger:active:not(:disabled) {\n  background-color: var(--_pressed-bg);\n}\n\n.trigger--open {\n  background-color: var(--_pressed-bg);\n}\n\n/* ── Trigger label ───────────────────────────────────────────────────────── */\n\n.trigger__label {\n  flex: 1;\n  min-width: 0;\n  overflow: hidden;\n  text-overflow: ellipsis;\n  white-space: nowrap;\n  text-align: left;\n  font-size: var(--typography-fontsize-md);\n  line-height: var(--typography-lineheight-md);\n  font-weight: var(--typography-weight-regular);\n  color: var(--color-foreground-primary);\n}\n\n.trigger__label--placeholder {\n  color: var(--color-foreground-secondary);\n}\n\n/* ── Chevron icon ────────────────────────────────────────────────────────── */\n\n.trigger__chevron {\n  flex-shrink: 0;\n  color: var(--color-foreground-secondary);\n  transition: transform var(--effect-motion-short-2);\n}\n\n.trigger--open .trigger__chevron {\n  transform: rotate(180deg);\n}\n",
      "type": "registry:ui"
    },
    {
      "path": "src/wc/components/Select/Select.tsx",
      "content": "import { Component, Prop, State, Event, EventEmitter, Element, Watch, Listen, h, Host } from '@stencil/core';\nimport type { MenuItemData } from '../Menu/menu-types';\n\nexport interface SelectOption {\n  label: string;\n  value: string;\n}\n\n@Component({\n  tag: 'ds-select',\n  styleUrl: 'Select.css',\n  scoped: true,\n})\nexport class Select {\n  @Element() el!: HTMLElement;\n\n  /**\n   * Array of options. Set via JS property.\n   * @example el.options = [{ label: 'Apple', value: 'apple' }];\n   */\n  @Prop() options: SelectOption[] = [];\n\n  /** Currently selected value. */\n  @Prop({ mutable: true }) value: string = '';\n\n  /** Placeholder shown when no value is selected. */\n  @Prop() placeholder: string = 'Select option';\n\n  /** Disables interaction (25% opacity via ds-control-inactive). */\n  @Prop() isInactive: boolean = false;\n\n  @Prop({ attribute: 'aria-label' }) ariaLabel: string | undefined;\n  @Prop({ attribute: 'aria-labelledby' }) ariaLabelledby: string | undefined;\n\n  /** Emits the selected value string. */\n  @Event() dsChange!: EventEmitter<string>;\n\n  @State() private isOpen: boolean = false;\n\n  private triggerEl: HTMLButtonElement | null = null;\n  private menuEl: HTMLDsMenuElement | null = null;\n\n  componentDidLoad() {\n    // Wire up the menu anchor to the trigger button\n    if (this.menuEl && this.triggerEl) {\n      this.menuEl.anchor = this.triggerEl;\n    }\n    // Listen for menu selection events\n    this.menuEl?.addEventListener('dsSelect', (e: Event) => {\n      const detail = (e as CustomEvent<MenuItemData>).detail;\n      if (detail?.value !== undefined) {\n        this.value = String(detail.value);\n        this.dsChange.emit(this.value);\n      }\n      this.isOpen = false;\n    });\n    // Listen for menu close event\n    this.menuEl?.addEventListener('dsClose', () => {\n      this.isOpen = false;\n    });\n  }\n\n  @Watch('isOpen')\n  onIsOpenChange(open: boolean) {\n    if (this.menuEl) {\n      this.menuEl.open = open;\n    }\n  }\n\n  @Watch('options')\n  onOptionsChange() {\n    this.syncMenuItems();\n  }\n\n  @Watch('value')\n  onValueChange() {\n    this.syncMenuItems();\n  }\n\n  private syncMenuItems() {\n    if (!this.menuEl) return;\n    this.menuEl.items = this.options.map(opt => ({\n      label: opt.label,\n      value: opt.value,\n      isSelected: opt.value === this.value,\n    }));\n  }\n\n  private open() {\n    if (this.isInactive || !this.options.length) return;\n    // Sync menu width to trigger width\n    if (this.menuEl && this.triggerEl) {\n      this.menuEl.menuWidth = `${this.triggerEl.offsetWidth}px`;\n      this.menuEl.anchor = this.triggerEl;\n    }\n    this.syncMenuItems();\n    this.isOpen = true;\n  }\n\n  private close() {\n    this.isOpen = false;\n  }\n\n  private toggle() {\n    if (this.isOpen) {\n      this.close();\n    } else {\n      this.open();\n    }\n  }\n\n  @Listen('keydown')\n  handleKeyDown(e: KeyboardEvent) {\n    // Only handle keydown on the trigger button\n    if (document.activeElement !== this.triggerEl) return;\n\n    if (!this.isOpen) {\n      switch (e.key) {\n        case 'ArrowDown':\n        case 'ArrowUp':\n        case 'Enter':\n        case ' ':\n          e.preventDefault();\n          this.open();\n          break;\n      }\n    } else {\n      if (e.key === 'Escape') {\n        e.preventDefault();\n        this.close();\n        this.triggerEl?.focus();\n      }\n    }\n  }\n\n  private get selectedLabel(): string {\n    const found = this.options.find(o => o.value === this.value);\n    return found?.label ?? '';\n  }\n\n  private get hasSelection(): boolean {\n    return !!this.options.find(o => o.value === this.value);\n  }\n\n  render() {\n    const label = this.hasSelection ? this.selectedLabel : this.placeholder;\n    const showPlaceholder = !this.hasSelection;\n\n    return (\n      <Host class={{ 'select-host': true, 'ds-control-inactive': this.isInactive }}>\n        <button\n          ref={el => {\n            this.triggerEl = (el as HTMLButtonElement) ?? null;\n          }}\n          type=\"button\"\n          class={{ trigger: true, 'trigger--open': this.isOpen }}\n          disabled={this.isInactive}\n          role=\"combobox\"\n          aria-haspopup=\"listbox\"\n          aria-expanded={this.isOpen}\n          aria-label={this.ariaLabel}\n          aria-labelledby={this.ariaLabelledby}\n          onClick={() => this.toggle()}\n        >\n          <span class={{ 'trigger__label': true, 'trigger__label--placeholder': showPlaceholder }}>\n            {label}\n          </span>\n          <svg\n            class=\"trigger__chevron\"\n            width=\"16\"\n            height=\"16\"\n            viewBox=\"0 0 16 16\"\n            fill=\"none\"\n            aria-hidden=\"true\"\n          >\n            <path\n              d=\"M4 6L8 10L12 6\"\n              stroke=\"currentColor\"\n              stroke-width=\"1.25\"\n              stroke-linecap=\"round\"\n              stroke-linejoin=\"round\"\n            />\n          </svg>\n        </button>\n        <ds-menu\n          ref={el => {\n            this.menuEl = (el as HTMLDsMenuElement) ?? null;\n          }}\n          side=\"bottom\"\n          align=\"start\"\n        />\n      </Host>\n    );\n  }\n}\n",
      "type": "registry:ui"
    }
  ]
}